[
  {
    "name": "Technology",
    "tags": "technology"
  },
  {
    "name": "Programming",
    "tags": "programming"
  },
  {
    "name": "Web Development",
    "tags": "web-development"
  },
  {
    "name": "Design",
    "tags": "design"
  },
  {
    "name": "JavaScript",
    "tags": "javascript"
  },
  {
    "name": "React",
    "tags": "react"
  },
  {
    "name": "Python",
    "tags": "python"
  },
  {
    "name": "Java",
    "tags": "java"
  },
  {
    "name": "Data Science",
    "tags": "data-science"
  },
  {
    "name": "Machine Learning",
    "tags": "machine-learning"
  },
  {
    "name": "Artificial Intelligence",
    "tags": "artificial-intelligence"
  },
  {
    "name": "Mobile Development",
    "tags": "mobile-development"
  },
  {
    "name": "UI/UX",
    "tags": "ui-ux"
  },
  {
    "name": "Cybersecurity",
    "tags": "cybersecurity"
  },
  {
    "name": "Blockchain",
    "tags": "blockchain"
  },
  {
    "name": "Cloud Computing",
    "tags": "cloud-computing"
  },
  {
    "name": "DevOps",
    "tags": "devops"
  },
  {
    "name": "Open Source",
    "tags": "open-source"
  },
  {
    "name": "Startups",
    "tags": "startups"
  },
  {
    "name": "Digital Marketing",
    "tags": "digital-marketing"
  }
]